datasette_demo_dbs/__init__.py
datasette_demo_dbs-0.1.1.dist-info/licenses/LICENSE
datasette_demo_dbs-0.1.1.dist-info/METADATA
datasette_demo_dbs-0.1.1.dist-info/WHEEL
datasette_demo_dbs-0.1.1.dist-info/entry_points.txt
datasette_demo_dbs-0.1.1.dist-info/top_level.txt
datasette_demo_dbs-0.1.1.dist-info/RECORD
