Metadata-Version: 2.4
Name: datasette-demo-dbs
Version: 0.1.1
Summary: Fetch missing demo DBs from URLs when Datasette first starts
Author: Simon Willison
License-Expression: Apache-2.0
Project-URL: Homepage, https://github.com/datasette/datasette-demo-dbs
Project-URL: Changelog, https://github.com/datasette/datasette-demo-dbs/releases
Project-URL: Issues, https://github.com/datasette/datasette-demo-dbs/issues
Project-URL: CI, https://github.com/datasette/datasette-demo-dbs/actions
Classifier: Framework :: Datasette
Requires-Python: >=3.9
License-File: LICENSE
Requires-Dist: datasette
Provides-Extra: test
Requires-Dist: pytest; extra == "test"
Requires-Dist: pytest-asyncio; extra == "test"
Requires-Dist: pytest-httpx; extra == "test"
Dynamic: license-file
